senta/__init__.py
senta/train.py
senta/common/__init__.py
senta/common/args.py
senta/common/register.py
senta/common/rule.py
senta/config/infer.json
senta/data/__init__.py
senta/data/data_set.py
senta/data/field.py
senta/data/reader_config.py
senta/data/util_helper.py
senta/data/vocabulary.py
senta/data/data_set_reader/__init__.py
senta/data/data_set_reader/base_dataset_reader.py
senta/data/data_set_reader/basic_dataset_reader.py
senta/data/data_set_reader/basic_dataset_reader_without_fields.py
senta/data/data_set_reader/ernie_onesentclassification_dataset_reader_ch.py
senta/data/data_set_reader/ernie_onesentclassification_dataset_reader_en.py
senta/data/data_set_reader/ernie_pretrain_dataset_reader.py
senta/data/data_set_reader/ernie_skep_pretrain_dataset_reader.py
senta/data/data_set_reader/ernie_twosentclassification_dataset_reader_ch.py
senta/data/data_set_reader/ernie_twosentclassification_dataset_reader_en.py
senta/data/data_set_reader/roberta_pretrain_dataset_reader_en.py
senta/data/data_set_reader/roberta_skep_pretrain_dataset_reader_en.py
senta/data/data_set_reader/roberta_twosentclassification_dataset_reader_en.py
senta/data/field_reader/__init__.py
senta/data/field_reader/base_field_reader.py
senta/data/field_reader/custom_text_field_reader.py
senta/data/field_reader/ernie_classification_field_reader.py
senta/data/field_reader/ernie_seqlabel_label_field_reader.py
senta/data/field_reader/ernie_text_field_reader.py
senta/data/field_reader/generate_label_field_reader.py
senta/data/field_reader/scalar_array_field_reader.py
senta/data/field_reader/scalar_field_reader.py
senta/data/field_reader/text_field_reader.py
senta/data/tokenizer/__init__.py
senta/data/tokenizer/custom_tokenizer.py
senta/data/tokenizer/tokenization_spm.py
senta/data/tokenizer/tokenization_utils.py
senta/data/tokenizer/tokenization_wp.py
senta/data/tokenizer/tokenizer.py
senta/inference/__init__.py
senta/inference/inference.py
senta/metrics/__init__.py
senta/metrics/glue_eval.py
Senta-2.0.0.dist-info/AUTHORS
Senta-2.0.0.dist-info/LICENSE
Senta-2.0.0.dist-info/METADATA
Senta-2.0.0.dist-info/WHEEL
Senta-2.0.0.dist-info/top_level.txt
Senta-2.0.0.dist-info/RECORD
