Metadata-Version: 2.1
Name: Senta
Version: 2.0.0
Summary: A sentiment classification tools made by Baidu NLP.
Home-page: https://github.com/baidu/senta
Author: Baidu NLP
Author-email: gaocan01@baidu.com
License: Apache 2.0
Platform: any
Classifier: Programming Language :: Python :: 3.7
Requires-Python: >=3.7
Requires-Dist: nltk (==3.4.5)
Requires-Dist: numpy (==1.14.5)
Requires-Dist: six (==1.11.0)
Requires-Dist: scikit-learn (==0.20.4)
Requires-Dist: sentencepiece (==0.1.83)
